kmotions/__init__.py
kmotions/motions.py
kmotions/py.typed
kmotions-0.3.8.dist-info/licenses/LICENSE
kmotions-0.3.8.dist-info/METADATA
kmotions-0.3.8.dist-info/WHEEL
kmotions-0.3.8.dist-info/top_level.txt
kmotions-0.3.8.dist-info/RECORD
