Metadata-Version: 2.4
Name: kmotions
Version: 0.3.8
Summary: Keyframe motions for Kbot
Home-page: https://github.com/kscalelabs/kmotions
Author: Bart van Marum
Author-email: bart@kscale.dev
Requires-Python: >=3.11
License-File: LICENSE
Provides-Extra: dev
Requires-Dist: mypy; extra == "dev"
Requires-Dist: pytest; extra == "dev"
Requires-Dist: ruff; extra == "dev"
Dynamic: author
Dynamic: author-email
Dynamic: description
Dynamic: description-content-type
Dynamic: home-page
Dynamic: license-file
Dynamic: provides-extra
Dynamic: requires-python
Dynamic: summary
